Metadata-Version: 2.1
Name: timethat
Version: 1.1.5
Summary: A human friendly time calculator for functions and code blocks
Home-page: https://gitlab.com/mozgurbayhan/timethat
Author: Mehmet Ozgur Bayhan
Author-email: mozgurbayhan@gmail.com
License: BSD
Project-URL: Bug Reports, https://gitlab.com/mozgurbayhan/timethat/issues
Project-URL: Funding, https://www.losev.org.tr/bagis/Bagis.html
Project-URL: Say Thanks!, https://gitlab.com/mozgurbayhan/timethat
Project-URL: Source, https://gitlab.com/mozgurbayhan/timethat
Keywords: time  development tracker debug
Platform: UNKNOWN
Classifier: Development Status :: 5 - Production/Stable
Classifier: License :: OSI Approved :: BSD License
Classifier: Intended Audience :: Developers
Classifier: Topic :: Software Development :: Bug Tracking
Classifier: Programming Language :: Python :: 3.0
Classifier: Programming Language :: Python :: 3.1
Classifier: Programming Language :: Python :: 3.2
Classifier: Programming Language :: Python :: 3.3
Classifier: Programming Language :: Python :: 3.4
Classifier: Programming Language :: Python :: 3.5
Classifier: Programming Language :: Python :: 3.6
Classifier: Programming Language :: Python :: 3.7
Classifier: Programming Language :: Python :: 3.8
Classifier: Programming Language :: Python :: 3.9
Requires-Python: >=3
